{
    "key": "group_59b7c0b279b2a",
    "title": "Pagebuilder",
    "fields": [
        {
            "key": "field_59b7c1088e871",
            "label": "Builder",
            "name": "pagebuilder",
            "type": "flexible_content",
            "instructions": "",
            "required": 0,
            "conditional_logic": 0,
            "wrapper": {
                "width": "",
                "class": "",
                "id": ""
            },
            "layouts": {
                "5a390e686e133": {
                    "key": "5a390e686e133",
                    "name": "Hero",
                    "label": "Hero",
                    "display": "block",
                    "sub_fields": [
                        {
                            "key": "field_5a390e766e134",
                            "label": "",
                            "name": "",
                            "type": "clone",
                            "instructions": "",
                            "required": 0,
                            "conditional_logic": 0,
                            "wrapper": {
                                "width": "",
                                "class": "",
                                "id": ""
                            },
                            "clone": [
                                "group_5a390c2abc23d"
                            ],
                            "display": "seamless",
                            "layout": "block",
                            "prefix_label": 0,
                            "prefix_name": 0
                        }
                    ],
                    "min": "",
                    "max": ""
                },
                "59b7c143adb89": {
                    "key": "59b7c143adb89",
                    "name": "AlternatingBlock",
                    "label": "Alternating block",
                    "display": "block",
                    "sub_fields": [
                        {
                            "key": "field_5a391836e5608",
                            "label": "",
                            "name": "",
                            "type": "clone",
                            "instructions": "",
                            "required": 0,
                            "conditional_logic": 0,
                            "wrapper": {
                                "width": "",
                                "class": "",
                                "id": ""
                            },
                            "clone": [
                                "group_5a3917d1a34a0"
                            ],
                            "display": "seamless",
                            "layout": "block",
                            "prefix_label": 0,
                            "prefix_name": 0
                        }
                    ],
                    "min": "",
                    "max": ""
                }
            },
            "button_label": "Add block",
            "min": "",
            "max": ""
        }
    ],
    "location": [
        [
            {
                "param": "page_template",
                "operator": "==",
                "value": "pagebuilder.php"
            }
        ]
    ],
    "menu_order": 0,
    "position": "normal",
    "style": "default",
    "label_placement": "top",
    "instruction_placement": "label",
    "hide_on_screen": [
        "the_content"
    ],
    "active": 1,
    "description": "",
    "modified": 1513692299
}